{"swagger":"2.0","info":{"description":"Microservicio para la obtencion de facturas de una poliza.","version":"0.1.1","title":"Microservicio que consulta las facturas por poliza."},"host":"127.0.0.1:8080","basePath":"/","tags":[{"name":"factura-poliza-controller","description":"Factura Poliza Controller"}],"paths":{"/poliza/factura/descarga":{"post":{"tags":["factura-poliza-controller"],"summary":"descarga","operationId":"obtenerDocumentoUsingPOST","consumes":["application/json"],"produces":["*/*"],"parameters":[{"name":"idDocumento","in":"query","description":"idDocumento","required":true,"type":"string"},{"name":"tipo","in":"query","description":"tipo","required":true,"type":"string"}],"responses":{"200":{"description":"OK","schema":{"$ref":"#/definitions/ResponseEntity"}},"201":{"description":"Created"},"401":{"description":"Unauthorized"},"403":{"description":"Forbidden"},"404":{"description":"Not Found"}}}},"/poliza/facturas":{"post":{"tags":["factura-poliza-controller"],"summary":"facturas","operationId":"obtenerRelacionFacturasUsingPOST","consumes":["application/json"],"produces":["application/json"],"parameters":[{"in":"body","name":"filtroBusqueda","description":"filtroBusqueda","required":true,"schema":{"$ref":"#/definitions/FiltroBusquedaFacturaDto"}}],"responses":{"200":{"description":"OK","schema":{"$ref":"#/definitions/ResponseCfd"}},"201":{"description":"Created"},"401":{"description":"Unauthorized"},"403":{"description":"Forbidden"},"404":{"description":"Not Found"}}}}},"definitions":{"Cfd":{"type":"object","properties":{"estado":{"type":"string"},"fechaEmision":{"type":"string"},"id":{"type":"string"},"poliza":{"type":"string"},"ramo":{"type":"string"},"version":{"type":"string"}}},"ResponseEntity":{"type":"object","properties":{"body":{"type":"object"},"statusCode":{"type":"string","enum":["100","101","102","103","200","201","202","203","204","205","206","207","208","226","300","301","302","303","304","305","307","308","400","401","402","403","404","405","406","407","408","409","410","411","412","413","414","415","416","417","418","419","420","421","422","423","424","426","428","429","431","451","500","501","502","503","504","505","506","507","508","509","510","511"]},"statusCodeValue":{"type":"integer","format":"int32"}}},"FiltroBusquedaFacturaDto":{"type":"object","properties":{"fechaFin":{"type":"string"},"fechaInicio":{"type":"string"},"poliza":{"type":"string"},"ramo":{"type":"string"},"rfcReceptor":{"type":"string"},"version":{"type":"string"}}},"Cfds":{"type":"object","properties":{"cfd":{"type":"array","items":{"$ref":"#/definitions/Cfd"}}}},"InputStream":{"type":"object"},"ResponseCfd":{"type":"object","properties":{"cfds":{"$ref":"#/definitions/Cfds"}}},"File":{"type":"object","properties":{"absolute":{"type":"boolean"},"absoluteFile":{"type":"file"},"absolutePath":{"type":"string"},"canonicalFile":{"type":"file"},"canonicalPath":{"type":"string"},"directory":{"type":"boolean"},"file":{"type":"boolean"},"freeSpace":{"type":"integer","format":"int64"},"hidden":{"type":"boolean"},"name":{"type":"string"},"parent":{"type":"string"},"parentFile":{"type":"file"},"path":{"type":"string"},"totalSpace":{"type":"integer","format":"int64"},"usableSpace":{"type":"integer","format":"int64"}}},"URI":{"type":"object","properties":{"absolute":{"type":"boolean"},"authority":{"type":"string"},"fragment":{"type":"string"},"host":{"type":"string"},"opaque":{"type":"boolean"},"path":{"type":"string"},"port":{"type":"integer","format":"int32"},"query":{"type":"string"},"rawAuthority":{"type":"string"},"rawFragment":{"type":"string"},"rawPath":{"type":"string"},"rawQuery":{"type":"string"},"rawSchemeSpecificPart":{"type":"string"},"rawUserInfo":{"type":"string"},"scheme":{"type":"string"},"schemeSpecificPart":{"type":"string"},"userInfo":{"type":"string"}}},"URL":{"type":"object","properties":{"authority":{"type":"string"},"content":{"type":"object"},"defaultPort":{"type":"integer","format":"int32"},"file":{"type":"string"},"host":{"type":"string"},"path":{"type":"string"},"port":{"type":"integer","format":"int32"},"protocol":{"type":"string"},"query":{"type":"string"},"ref":{"type":"string"},"userInfo":{"type":"string"}}},"InputStreamResource":{"type":"object","properties":{"description":{"type":"string"},"file":{"type":"file"},"filename":{"type":"string"},"inputStream":{"$ref":"#/definitions/InputStream"},"open":{"type":"boolean"},"readable":{"type":"boolean"},"uri":{"$ref":"#/definitions/URI"},"url":{"$ref":"#/definitions/URL"}}}}}
